odoo9_addon_web_widget_color-9.0.1.0.0.99.dev2-py2.7-nspkg.pth
odoo_addons/web_widget_color/__openerp__.py
odoo_addons/web_widget_color/__init__.py
odoo_addons/web_widget_color/README.rst
odoo_addons/web_widget_color/view/web_widget_color_view.xml
odoo_addons/web_widget_color/images/form_view.png
odoo_addons/web_widget_color/images/picker.png
odoo_addons/web_widget_color/images/list_view.png
odoo_addons/web_widget_color/static/description/icon.png
odoo_addons/web_widget_color/static/lib/jscolor/demo.html
odoo_addons/web_widget_color/static/lib/jscolor/arrow.gif
odoo_addons/web_widget_color/static/lib/jscolor/hv.png
odoo_addons/web_widget_color/static/lib/jscolor/hs.png
odoo_addons/web_widget_color/static/lib/jscolor/cross.gif
odoo_addons/web_widget_color/static/lib/jscolor/jscolor.js
odoo_addons/web_widget_color/static/src/js/widget.js
odoo_addons/web_widget_color/static/src/css/widget.css
odoo_addons/web_widget_color/static/src/xml/widget.xml
odoo9_addon_web_widget_color-9.0.1.0.0.99.dev2.dist-info/top_level.txt
odoo9_addon_web_widget_color-9.0.1.0.0.99.dev2.dist-info/WHEEL
odoo9_addon_web_widget_color-9.0.1.0.0.99.dev2.dist-info/RECORD
odoo9_addon_web_widget_color-9.0.1.0.0.99.dev2.dist-info/metadata.json
odoo9_addon_web_widget_color-9.0.1.0.0.99.dev2.dist-info/DESCRIPTION.rst
odoo9_addon_web_widget_color-9.0.1.0.0.99.dev2.dist-info/METADATA
odoo9_addon_web_widget_color-9.0.1.0.0.99.dev2.dist-info/namespace_packages.txt
